{
  "screenSize": {
    "width": 750,
    "height": 1334
  },
  "gameArea": {
    "width": 750,
    "height": 1067
  },
  "uiArea": {
    "height": 266
  },
  "maps": [
    {
      "id": 1,
      "name": "经典随机",
      "file": "data_1_经典随机.js",
      "stats": {
        "missions": 38,
        "enemies": 22,
        "shops": 8,
        "specials": 12
      }
    },
    {
      "id": 2,
      "name": "区域划分",
      "file": "data_2_区域划分.js",
      "stats": {
        "missions": 20,
        "enemies": 14,
        "shops": 8,
        "specials": 12
      }
    },
    {
      "id": 3,
      "name": "螺旋进阶",
      "file": "data_3_螺旋进阶.js",
      "stats": {
        "missions": 36,
        "enemies": 27,
        "shops": 5,
        "specials": 12
      }
    },
    {
      "id": 4,
      "name": "迷宫通道",
      "file": "data_4_迷宫通道.js",
      "stats": {
        "missions": 21,
        "enemies": 7,
        "shops": 8,
        "specials": 12
      }
    },
    {
      "id": 5,
      "name": "塔防路径",
      "file": "data_5_塔防路径.js",
      "stats": {
        "missions": 40,
        "enemies": 24,
        "shops": 8,
        "specials": 12
      }
    }
  ]
}